odoo10_addon_sale_order_lot_selection-10.0.1.0.1-py3.8-nspkg.pth
odoo/addons/sale_order_lot_selection/README.rst
odoo/addons/sale_order_lot_selection/__init__.py
odoo/addons/sale_order_lot_selection/__manifest__.py
odoo/addons/sale_order_lot_selection/i18n/ca.po
odoo/addons/sale_order_lot_selection/i18n/de.po
odoo/addons/sale_order_lot_selection/i18n/el_GR.po
odoo/addons/sale_order_lot_selection/i18n/en.po
odoo/addons/sale_order_lot_selection/i18n/es.po
odoo/addons/sale_order_lot_selection/i18n/es_ES.po
odoo/addons/sale_order_lot_selection/i18n/es_MX.po
odoo/addons/sale_order_lot_selection/i18n/es_VE.po
odoo/addons/sale_order_lot_selection/i18n/fi.po
odoo/addons/sale_order_lot_selection/i18n/fr.po
odoo/addons/sale_order_lot_selection/i18n/gl.po
odoo/addons/sale_order_lot_selection/i18n/hr.po
odoo/addons/sale_order_lot_selection/i18n/hr_HR.po
odoo/addons/sale_order_lot_selection/i18n/hu.po
odoo/addons/sale_order_lot_selection/i18n/it.po
odoo/addons/sale_order_lot_selection/i18n/nl.po
odoo/addons/sale_order_lot_selection/i18n/nl_NL.po
odoo/addons/sale_order_lot_selection/i18n/pt.po
odoo/addons/sale_order_lot_selection/i18n/pt_BR.po
odoo/addons/sale_order_lot_selection/i18n/pt_PT.po
odoo/addons/sale_order_lot_selection/i18n/ro.po
odoo/addons/sale_order_lot_selection/i18n/sale_order_lot_selection.pot
odoo/addons/sale_order_lot_selection/i18n/sk.po
odoo/addons/sale_order_lot_selection/i18n/sl.po
odoo/addons/sale_order_lot_selection/i18n/tr.po
odoo/addons/sale_order_lot_selection/i18n/tr_TR.po
odoo/addons/sale_order_lot_selection/i18n/vi_VN.po
odoo/addons/sale_order_lot_selection/i18n/zh_CN.po
odoo/addons/sale_order_lot_selection/model/__init__.py
odoo/addons/sale_order_lot_selection/model/procurement.py
odoo/addons/sale_order_lot_selection/model/sale.py
odoo/addons/sale_order_lot_selection/model/stock.py
odoo/addons/sale_order_lot_selection/static/description/icon.png
odoo/addons/sale_order_lot_selection/tests/__init__.py
odoo10_addon_sale_order_lot_selection-10.0.1.0.1.dist-info/METADATA
odoo10_addon_sale_order_lot_selection-10.0.1.0.1.dist-info/WHEEL
odoo10_addon_sale_order_lot_selection-10.0.1.0.1.dist-info/namespace_packages.txt
odoo10_addon_sale_order_lot_selection-10.0.1.0.1.dist-info/top_level.txt
odoo10_addon_sale_order_lot_selection-10.0.1.0.1.dist-info/RECORD
